usb_plug_notification.py
usb_plug_notification-0.1.0.dist-info/WHEEL
usb_plug_notification-0.1.0.dist-info/METADATA
usb_plug_notification-0.1.0.dist-info/RECORD
