Metadata-Version: 2.1
Name: usb-plug-notification
Version: 0.1.0
Summary: USB plug notification package
License: GPL-3.0-or-later
Author: Dick Marinus
Author-email: dick@mrns.nl
Requires-Python: >=3.9,<4.0
Classifier: License :: OSI Approved :: GNU General Public License v3 or later (GPLv3+)
Classifier: Programming Language :: Python :: 3
Classifier: Programming Language :: Python :: 3.9
